Metadata-Version: 2.1
Name: springboottt
Version: 1.3
Summary: this is springboottt
Home-page: 
Download-URL: 
Author: 
Author-email: 
License: MIT
Keywords: springboottt
Classifier: Intended Audience :: Developers
Classifier: Topic :: Software Development :: Build Tools
Classifier: License :: OSI Approved :: MIT License
Classifier: Programming Language :: Python :: 3
License-File: LICENSE.txt
